wagtail_periodic_review/__init__.py
wagtail_periodic_review/apps.py
wagtail_periodic_review/filters.py
wagtail_periodic_review/models.py
wagtail_periodic_review/utils.py
wagtail_periodic_review/views.py
wagtail_periodic_review/wagtail_hooks.py
wagtail_periodic_review/widgets.py
wagtail_periodic_review/migrations/0001_initial.py
wagtail_periodic_review/migrations/__init__.py
wagtail_periodic_review/templates/reports/periodic_review_report_results.html
wagtail_periodic_review/templates/reports/includes/list_with_review_dates.html
wagtail_periodic_review/templates/wagtail_periodic_review/icons/calendar-stats.svg
wagtail_periodic_review/templates/wagtailadmin/periodic_review/home_panel.html
wagtail_periodic_review-0.5.0.dist-info/licenses/LICENSE
wagtail_periodic_review-0.5.0.dist-info/WHEEL
wagtail_periodic_review-0.5.0.dist-info/METADATA
wagtail_periodic_review-0.5.0.dist-info/RECORD
