Metadata-Version: 2.4
Name: wagtail-periodic-review
Version: 0.5.0
Summary: A Wagtail package for periodic page content reviews
Keywords: Wagtail,Django,content,review
Author-email: Andy Babic <andy.babic@torchbox.com>
Maintainer-email: Dan Braghis <dan.braghis@torchbox.com>
Requires-Python: >=3.9
License-Expression: BSD-3-Clause
Classifier: Development Status :: 4 - Beta
Classifier: Environment :: Web Environment
Classifier: Intended Audience :: Developers
Classifier: Operating System :: OS Independent
Classifier: Framework :: Django
Classifier: Framework :: Django :: 4.2
Classifier: Framework :: Django :: 5.1
Classifier: Framework :: Django :: 5.2
Classifier: Framework :: Wagtail
Classifier: Framework :: Wagtail :: 6
Classifier: Framework :: Wagtail :: 7
Classifier: Programming Language :: Python :: 3
Classifier: Programming Language :: Python :: 3.9
Classifier: Programming Language :: Python :: 3.10
Classifier: Programming Language :: Python :: 3.11
Classifier: Programming Language :: Python :: 3.12
Classifier: Programming Language :: Python :: 3.13
License-File: LICENSE
Requires-Dist: Wagtail>=6.3
Requires-Dist: python-dateutil>=2.8,<3.0.0
Project-URL: Changelog, https://github.com/torchbox/wagtail-periodic-review/blob/main/CHANGELOG.md
Project-URL: Source, https://github.com/torchbox/wagtail-periodic-review/blob/main/CHANGELOG.md
